{
  "salary_data": [
    {
      "orgNs10Code": 26,
      "orgNs11Code": 5,
      "orgName": "\"SUV SPORTI TURLARI BO`YICHA RESPUBLIKA OLIY SPORT MAHORATI MAKTABI\"",
      "orgTin": "200540462",
      "tin": null,
      "year": 2023,
      "period": 7,
      "salary": 1083880,
      "salaryTaxSum": 130066,
      "inpsSum": null,
      "pinfl": "51901016050048",
      "positionName": "шофер",
      "status": 1,
      "contractType": 1,
      "rate": 1,
      "workType": 1,
      "service_id": 8
    },
    {
      "orgNs10Code": 26,
      "orgNs11Code": 5,
      "orgName": "\"SUV SPORTI TURLARI BO`YICHA RESPUBLIKA OLIY SPORT MAHORATI MAKTABI\"",
      "orgTin": "200540462",
      "tin": null,
      "year": 2023,
      "period": 8,
      "salary": 7417740,
      "salaryTaxSum": 890128,
      "inpsSum": null,
      "pinfl": "51901016050048",
      "positionName": "шофер",
      "status": 1,
      "contractType": 1,
      "rate": 1,
      "workType": 1,
      "service_id": 8
    },
    {
      "orgNs10Code": 26,
      "orgNs11Code": 5,
      "orgName": "\"SUV SPORTI TURLARI BO`YICHA RESPUBLIKA OLIY SPORT MAHORATI MAKTABI\"",
      "orgTin": "200540462",
      "tin": null,
      "year": 2023,
      "period": 9,
      "salary": 3450000,
      "salaryTaxSum": 414000,
      "inpsSum": null,
      "pinfl": "51901016050048",
      "positionName": "шофер",
      "status": 1,
      "contractType": 1,
      "rate": 1,
      "workType": 1,
      "service_id": 8
    },
    {
      "orgNs10Code": 26,
      "orgNs11Code": 5,
      "orgName": "\"SUV SPORTI TURLARI BO`YICHA RESPUBLIKA OLIY SPORT MAHORATI MAKTABI\"",
      "orgTin": "200540462",
      "tin": null,
      "year": 2023,
      "period": 10,
      "salary": 2970000,
      "salaryTaxSum": 356400,
      "inpsSum": null,
      "pinfl": "51901016050048",
      "positionName": "шофер",
      "status": 1,
      "contractType": 1,
      "rate": 1,
      "workType": 1,
      "service_id": 8
    },
    {
      "orgNs10Code": 26,
      "orgNs11Code": 5,
      "orgName": "\"SUV SPORTI TURLARI BO`YICHA RESPUBLIKA OLIY SPORT MAHORATI MAKTABI\"",
      "orgTin": "200540462",
      "tin": null,
      "year": 2023,
      "period": 11,
      "salary": 9548960,
      "salaryTaxSum": 1145876,
      "inpsSum": null,
      "pinfl": "51901016050048",
      "positionName": "шофер",
      "status": 1,
      "contractType": 1,
      "rate": 1,
      "workType": 1,
      "service_id": 8
    },
    {
      "orgNs10Code": 26,
      "orgNs11Code": 5,
      "orgName": "\"SUV SPORTI TURLARI BO`YICHA RESPUBLIKA OLIY SPORT MAHORATI MAKTABI\"",
      "orgTin": "200540462",
      "tin": null,
      "year": 2023,
      "period": 12,
      "salary": 7856693,
      "salaryTaxSum": 942803,
      "inpsSum": null,
      "pinfl": "51901016050048",
      "positionName": "шофер",
      "status": 2,
      "contractType": 1,
      "rate": 1,
      "workType": 1,
      "service_id": 8
    },
    {
      "orgNs10Code": 26,
      "orgNs11Code": 5,
      "orgName": "\"SUV SPORTI TURLARI BO`YICHA RESPUBLIKA OLIY SPORT MAHORATI MAKTABI\"",
      "orgTin": "200540462",
      "tin": null,
      "year": 2024,
      "period": 1,
      "salary": 6536493,
      "salaryTaxSum": 784379,
      "inpsSum": null,
      "pinfl": "51901016050048",
      "positionName": "шофер",
      "status": 1,
      "contractType": 1,
      "rate": 1,
      "workType": 1,
      "service_id": 8
    },
    {
      "orgNs10Code": 26,
      "orgNs11Code": 5,
      "orgName": "\"SUV SPORTI TURLARI BO`YICHA RESPUBLIKA OLIY SPORT MAHORATI MAKTABI\"",
      "orgTin": "200540462",
      "tin": null,
      "year": 2024,
      "period": 2,
      "salary": 7083293,
      "salaryTaxSum": 849995,
      "inpsSum": null,
      "pinfl": "51901016050048",
      "positionName": "шофер",
      "status": 1,
      "contractType": 1,
      "rate": 1,
      "workType": 1,
      "service_id": 8
    },
    {
      "orgNs10Code": 26,
      "orgNs11Code": 5,
      "orgName": "\"SUV SPORTI TURLARI BO`YICHA RESPUBLIKA OLIY SPORT MAHORATI MAKTABI\"",
      "orgTin": "200540462",
      "tin": null,
      "year": 2024,
      "period": 3,
      "salary": 7407120,
      "salaryTaxSum": 888855,
      "inpsSum": null,
      "pinfl": "51901016050048",
      "positionName": "шофер",
      "status": 1,
      "contractType": 1,
      "rate": 1,
      "workType": 1,
      "service_id": 8
    },
    {
      "orgNs10Code": 26,
      "orgNs11Code": 5,
      "orgName": "\"SUV SPORTI TURLARI BO`YICHA RESPUBLIKA OLIY SPORT MAHORATI MAKTABI\"",
      "orgTin": "200540462",
      "tin": null,
      "year": 2024,
      "period": 4,
      "salary": 5760800,
      "salaryTaxSum": 691296,
      "inpsSum": null,
      "pinfl": "51901016050048",
      "positionName": "шофер",
      "status": 1,
      "contractType": 1,
      "rate": 1,
      "workType": 1,
      "service_id": 8
    },
    {
      "orgNs10Code": 26,
      "orgNs11Code": 5,
      "orgName": "\"SUV SPORTI TURLARI BO`YICHA RESPUBLIKA OLIY SPORT MAHORATI MAKTABI\"",
      "orgTin": "200540462",
      "tin": null,
      "year": 2024,
      "period": 5,
      "salary": 4032000,
      "salaryTaxSum": 483840,
      "inpsSum": null,
      "pinfl": "51901016050048",
      "positionName": "шофер",
      "status": 1,
      "contractType": 1,
      "rate": 1,
      "workType": 1,
      "service_id": 8
    },
    {
      "orgNs10Code": 26,
      "orgNs11Code": 5,
      "orgName": "\"SUV SPORTI TURLARI BO`YICHA RESPUBLIKA OLIY SPORT MAHORATI MAKTABI\"",
      "orgTin": "200540462",
      "tin": null,
      "year": 2024,
      "period": 6,
      "salary": 4032000,
      "salaryTaxSum": 483840,
      "inpsSum": null,
      "pinfl": "51901016050048",
      "positionName": "Ҳайдовчи (енгил машина)",
      "status": 1,
      "contractType": 1,
      "rate": 1,
      "workType": 1,
      "service_id": 8
    },
    {
      "orgNs10Code": 26,
      "orgNs11Code": 5,
      "orgName": "\"SUV SPORTI TURLARI BO`YICHA RESPUBLIKA OLIY SPORT MAHORATI MAKTABI\"",
      "orgTin": "200540462",
      "tin": null,
      "year": 2024,
      "period": 7,
      "salary": 4489800,
      "salaryTaxSum": 538776,
      "inpsSum": null,
      "pinfl": "51901016050048",
      "positionName": "Ҳайдовчи (енгил машина)",
      "status": 1,
      "contractType": 1,
      "rate": 1,
      "workType": 1,
      "service_id": 8
    },
    {
      "orgNs10Code": 26,
      "orgNs11Code": 5,
      "orgName": "\"SUV SPORTI TURLARI BO`YICHA RESPUBLIKA OLIY SPORT MAHORATI MAKTABI\"",
      "orgTin": "200540462",
      "tin": null,
      "year": 2024,
      "period": 8,
      "salary": 4510800,
      "salaryTaxSum": 541296,
      "inpsSum": null,
      "pinfl": "51901016050048",
      "positionName": "Ҳайдовчи (енгил машина)",
      "status": 1,
      "contractType": 1,
      "rate": 1,
      "workType": 1,
      "service_id": 8
    },
    {
      "orgNs10Code": 26,
      "orgNs11Code": 5,
      "orgName": "\"SUV SPORTI TURLARI BO`YICHA RESPUBLIKA OLIY SPORT MAHORATI MAKTABI\"",
      "orgTin": "200540462",
      "tin": null,
      "year": 2024,
      "period": 9,
      "salary": 5155500,
      "salaryTaxSum": 618660,
      "inpsSum": null,
      "pinfl": "51901016050048",
      "positionName": "Енгил автомобиль ҳайдовчиси",
      "status": 1,
      "contractType": 1,
      "rate": 1,
      "workType": 1,
      "service_id": 8
    },
    {
      "orgNs10Code": 26,
      "orgNs11Code": 5,
      "orgName": "\"SUV SPORTI TURLARI BO`YICHA RESPUBLIKA OLIY SPORT MAHORATI MAKTABI\"",
      "orgTin": "200540462",
      "tin": null,
      "year": 2024,
      "period": 10,
      "salary": 4919746,
      "salaryTaxSum": 590369.52,
      "inpsSum": null,
      "pinfl": "51901016050048",
      "positionName": "Енгил автомашина ҳайдовчиси",
      "status": 1,
      "contractType": 1,
      "rate": 1,
      "workType": 1,
      "service_id": 8
    },
    {
      "orgNs10Code": 26,
      "orgNs11Code": 5,
      "orgName": "\"SUV SPORTI TURLARI BO`YICHA RESPUBLIKA OLIY SPORT MAHORATI MAKTABI\"",
      "orgTin": "200540462",
      "tin": null,
      "year": 2024,
      "period": 11,
      "salary": 2609746,
      "salaryTaxSum": 313169,
      "inpsSum": null,
      "pinfl": "51901016050048",
      "positionName": "Енгил автомобиль ҳайдовчиси",
      "status": 1,
      "contractType": 1,
      "rate": 1,
      "workType": 1,
      "service_id": 8
    },
    {
      "orgNs10Code": 26,
      "orgNs11Code": 5,
      "orgName": "\"SUV SPORTI TURLARI BO`YICHA RESPUBLIKA OLIY SPORT MAHORATI MAKTABI\"",
      "orgTin": "200540462",
      "tin": null,
      "year": 2023,
      "period": 7,
      "salary": 1083880,
      "salaryTaxSum": 130066,
      "inpsSum": null,
      "pinfl": "51901016050048",
      "positionName": "шофер",
      "status": 1,
      "contractType": 1,
      "rate": 1,
      "workType": 1,
      "service_id": 8
    },
    {
      "orgNs10Code": 26,
      "orgNs11Code": 5,
      "orgName": "\"SUV SPORTI TURLARI BO`YICHA RESPUBLIKA OLIY SPORT MAHORATI MAKTABI\"",
      "orgTin": "200540462",
      "tin": null,
      "year": 2023,
      "period": 8,
      "salary": 7417740,
      "salaryTaxSum": 890128,
      "inpsSum": null,
      "pinfl": "51901016050048",
      "positionName": "шофер",
      "status": 1,
      "contractType": 1,
      "rate": 1,
      "workType": 1,
      "service_id": 8
    },
    {
      "orgNs10Code": 26,
      "orgNs11Code": 5,
      "orgName": "\"SUV SPORTI TURLARI BO`YICHA RESPUBLIKA OLIY SPORT MAHORATI MAKTABI\"",
      "orgTin": "200540462",
      "tin": null,
      "year": 2023,
      "period": 9,
      "salary": 3450000,
      "salaryTaxSum": 414000,
      "inpsSum": null,
      "pinfl": "51901016050048",
      "positionName": "шофер",
      "status": 1,
      "contractType": 1,
      "rate": 1,
      "workType": 1,
      "service_id": 8
    },
    {
      "orgNs10Code": 26,
      "orgNs11Code": 5,
      "orgName": "\"SUV SPORTI TURLARI BO`YICHA RESPUBLIKA OLIY SPORT MAHORATI MAKTABI\"",
      "orgTin": "200540462",
      "tin": null,
      "year": 2023,
      "period": 10,
      "salary": 2970000,
      "salaryTaxSum": 356400,
      "inpsSum": null,
      "pinfl": "51901016050048",
      "positionName": "шофер",
      "status": 1,
      "contractType": 1,
      "rate": 1,
      "workType": 1,
      "service_id": 8
    },
    {
      "orgNs10Code": 26,
      "orgNs11Code": 5,
      "orgName": "\"SUV SPORTI TURLARI BO`YICHA RESPUBLIKA OLIY SPORT MAHORATI MAKTABI\"",
      "orgTin": "200540462",
      "tin": null,
      "year": 2023,
      "period": 11,
      "salary": 9548960,
      "salaryTaxSum": 1145876,
      "inpsSum": null,
      "pinfl": "51901016050048",
      "positionName": "шофер",
      "status": 1,
      "contractType": 1,
      "rate": 1,
      "workType": 1,
      "service_id": 8
    },
    {
      "orgNs10Code": 26,
      "orgNs11Code": 5,
      "orgName": "\"SUV SPORTI TURLARI BO`YICHA RESPUBLIKA OLIY SPORT MAHORATI MAKTABI\"",
      "orgTin": "200540462",
      "tin": null,
      "year": 2023,
      "period": 12,
      "salary": 7856693,
      "salaryTaxSum": 942803,
      "inpsSum": null,
      "pinfl": "51901016050048",
      "positionName": "шофер",
      "status": 2,
      "contractType": 1,
      "rate": 1,
      "workType": 1,
      "service_id": 8
    },
    {
      "orgNs10Code": 26,
      "orgNs11Code": 5,
      "orgName": "\"SUV SPORTI TURLARI BO`YICHA RESPUBLIKA OLIY SPORT MAHORATI MAKTABI\"",
      "orgTin": "200540462",
      "tin": null,
      "year": 2024,
      "period": 1,
      "salary": 6536493,
      "salaryTaxSum": 784379,
      "inpsSum": null,
      "pinfl": "51901016050048",
      "positionName": "шофер",
      "status": 1,
      "contractType": 1,
      "rate": 1,
      "workType": 1,
      "service_id": 8
    },
    {
      "orgNs10Code": 26,
      "orgNs11Code": 5,
      "orgName": "\"SUV SPORTI TURLARI BO`YICHA RESPUBLIKA OLIY SPORT MAHORATI MAKTABI\"",
      "orgTin": "200540462",
      "tin": null,
      "year": 2024,
      "period": 2,
      "salary": 7083293,
      "salaryTaxSum": 849995,
      "inpsSum": null,
      "pinfl": "51901016050048",
      "positionName": "шофер",
      "status": 1,
      "contractType": 1,
      "rate": 1,
      "workType": 1,
      "service_id": 8
    },
    {
      "orgNs10Code": 26,
      "orgNs11Code": 5,
      "orgName": "\"SUV SPORTI TURLARI BO`YICHA RESPUBLIKA OLIY SPORT MAHORATI MAKTABI\"",
      "orgTin": "200540462",
      "tin": null,
      "year": 2024,
      "period": 3,
      "salary": 7407120,
      "salaryTaxSum": 888855,
      "inpsSum": null,
      "pinfl": "51901016050048",
      "positionName": "шофер",
      "status": 1,
      "contractType": 1,
      "rate": 1,
      "workType": 1,
      "service_id": 8
    },
    {
      "orgNs10Code": 26,
      "orgNs11Code": 5,
      "orgName": "\"SUV SPORTI TURLARI BO`YICHA RESPUBLIKA OLIY SPORT MAHORATI MAKTABI\"",
      "orgTin": "200540462",
      "tin": null,
      "year": 2024,
      "period": 4,
      "salary": 5760800,
      "salaryTaxSum": 691296,
      "inpsSum": null,
      "pinfl": "51901016050048",
      "positionName": "шофер",
      "status": 1,
      "contractType": 1,
      "rate": 1,
      "workType": 1,
      "service_id": 8
    },
    {
      "orgNs10Code": 26,
      "orgNs11Code": 5,
      "orgName": "\"SUV SPORTI TURLARI BO`YICHA RESPUBLIKA OLIY SPORT MAHORATI MAKTABI\"",
      "orgTin": "200540462",
      "tin": null,
      "year": 2024,
      "period": 5,
      "salary": 4032000,
      "salaryTaxSum": 483840,
      "inpsSum": null,
      "pinfl": "51901016050048",
      "positionName": "шофер",
      "status": 1,
      "contractType": 1,
      "rate": 1,
      "workType": 1,
      "service_id": 8
    },
    {
      "orgNs10Code": 26,
      "orgNs11Code": 5,
      "orgName": "\"SUV SPORTI TURLARI BO`YICHA RESPUBLIKA OLIY SPORT MAHORATI MAKTABI\"",
      "orgTin": "200540462",
      "tin": null,
      "year": 2024,
      "period": 6,
      "salary": 4032000,
      "salaryTaxSum": 483840,
      "inpsSum": null,
      "pinfl": "51901016050048",
      "positionName": "Ҳайдовчи (енгил машина)",
      "status": 1,
      "contractType": 1,
      "rate": 1,
      "workType": 1,
      "service_id": 8
    },
    {
      "orgNs10Code": 26,
      "orgNs11Code": 5,
      "orgName": "\"SUV SPORTI TURLARI BO`YICHA RESPUBLIKA OLIY SPORT MAHORATI MAKTABI\"",
      "orgTin": "200540462",
      "tin": null,
      "year": 2024,
      "period": 7,
      "salary": 4489800,
      "salaryTaxSum": 538776,
      "inpsSum": null,
      "pinfl": "51901016050048",
      "positionName": "Ҳайдовчи (енгил машина)",
      "status": 1,
      "contractType": 1,
      "rate": 1,
      "workType": 1,
      "service_id": 8
    },
    {
      "orgNs10Code": 26,
      "orgNs11Code": 5,
      "orgName": "\"SUV SPORTI TURLARI BO`YICHA RESPUBLIKA OLIY SPORT MAHORATI MAKTABI\"",
      "orgTin": "200540462",
      "tin": null,
      "year": 2024,
      "period": 8,
      "salary": 4510800,
      "salaryTaxSum": 541296,
      "inpsSum": null,
      "pinfl": "51901016050048",
      "positionName": "Ҳайдовчи (енгил машина)",
      "status": 1,
      "contractType": 1,
      "rate": 1,
      "workType": 1,
      "service_id": 8
    },
    {
      "orgNs10Code": 26,
      "orgNs11Code": 5,
      "orgName": "\"SUV SPORTI TURLARI BO`YICHA RESPUBLIKA OLIY SPORT MAHORATI MAKTABI\"",
      "orgTin": "200540462",
      "tin": null,
      "year": 2024,
      "period": 9,
      "salary": 5155500,
      "salaryTaxSum": 618660,
      "inpsSum": null,
      "pinfl": "51901016050048",
      "positionName": "Енгил автомобиль ҳайдовчиси",
      "status": 1,
      "contractType": 1,
      "rate": 1,
      "workType": 1,
      "service_id": 8
    },
    {
      "orgNs10Code": 26,
      "orgNs11Code": 5,
      "orgName": "\"SUV SPORTI TURLARI BO`YICHA RESPUBLIKA OLIY SPORT MAHORATI MAKTABI\"",
      "orgTin": "200540462",
      "tin": null,
      "year": 2024,
      "period": 10,
      "salary": 4919746,
      "salaryTaxSum": 590369.52,
      "inpsSum": null,
      "pinfl": "51901016050048",
      "positionName": "Енгил автомашина ҳайдовчиси",
      "status": 1,
      "contractType": 1,
      "rate": 1,
      "workType": 1,
      "service_id": 8
    },
    {
      "orgNs10Code": 26,
      "orgNs11Code": 5,
      "orgName": "\"SUV SPORTI TURLARI BO`YICHA RESPUBLIKA OLIY SPORT MAHORATI MAKTABI\"",
      "orgTin": "200540462",
      "tin": null,
      "year": 2024,
      "period": 11,
      "salary": 2609746,
      "salaryTaxSum": 313169,
      "inpsSum": null,
      "pinfl": "51901016050048",
      "positionName": "Енгил автомобиль ҳайдовчиси",
      "status": 1,
      "contractType": 1,
      "rate": 1,
      "workType": 1,
      "service_id": 8
    }
  ]
}